plytix
