Metadata-Version: 1.1
Name: plytix-retailers-sdk
Version: 1.0.3
Summary: Plytix Retailers SDK for Python
Home-page: https://bitbucket.org/plytixdevs/plytix-sdk-python
Author: Daniel Sánchez Prolongo
Author-email: dani@plytix.com
License: MIT
Keywords: plytix
Platform: UNKNOWN
Classifier: Development Status :: 4 - Beta
Classifier: Intended Audience :: Developers
Classifier: License :: OSI Approved :: MIT License
Classifier: Natural Language :: English
Classifier: Programming Language :: Python :: 2
Classifier: Programming Language :: Python :: 2.7
Classifier: Programming Language :: Python :: 3
Classifier: Programming Language :: Python :: 3.4
